<plominodatabase id="iol_suap">
  <design>
    <element id="allegati-subingresso" title="allegati-subingresso" type="PlominoForm">
      <id type="Products.Archetypes.Field.StringField">allegati-subingresso</id>
      <onCreateDocument type="Products.Archetypes.Field.TextField"><![CDATA[]]></onCreateDocument>
      <onOpenDocument type="Products.Archetypes.Field.TextField"><![CDATA[]]></onOpenDocument>
      <beforeSaveDocument type="Products.Archetypes.Field.TextField"><![CDATA[########## IMPORTANTE SETTO UN ITEM CON IL NOME DELLA FORM PER RISETTARE LA FORM DOPO IL SALVATAGGIO 
context.setItem('IOL_PREVIOUS_FORM',context.getItem('Form'))]]></beforeSaveDocument>
      <onSaveDocument type="Products.Archetypes.Field.TextField"><![CDATA[########## IMPORTANTE SETTO LA FORM PRECEDENTE ALL'APERTURA 
context.setItem('Form',context.getItem('IOL_PREVIOUS_FORM'))
context.removeItem('IOL_PREVIOUS_FORM')
return "%s/EditDocument?openwithform=00-completata" %context.absolute_url()]]></onSaveDocument>
      <onDeleteDocument type="Products.Archetypes.Field.TextField"><![CDATA[]]></onDeleteDocument>
      <onSearch type="Products.Archetypes.Field.TextField"><![CDATA[]]></onSearch>
      <beforeCreateDocument type="Products.Archetypes.Field.TextField"><![CDATA[]]></beforeCreateDocument>
      <FormLayout type="Products.Archetypes.Field.TextField"><![CDATA[<fieldset class="scheduler-border" title="Richiedente">
<legend class="scheduler-border">DOCUMENTAZIONE ALLEGATA ALLA SCIA</legend>
<p><span class="plominoSubformClass">base_sub_allegati_ci</span></p>
<p><span class="plominoSubformClass">base_sub_allegati_requisiti_professionali</span></p>
</fieldset>]]></FormLayout>
      <FormMethod type="Products.Archetypes.Field.TextField"><![CDATA[Auto]]></FormMethod>
      <DocumentTitle type="Products.Archetypes.Field.TextField"><![CDATA[]]></DocumentTitle>
      <DynamicDocumentTitle type="Products.Archetypes.Field.BooleanField">False</DynamicDocumentTitle>
      <StoreDynamicDocumentTitle type="Products.Archetypes.Field.BooleanField">False</StoreDynamicDocumentTitle>
      <DocumentId type="Products.Archetypes.Field.TextField"><![CDATA[]]></DocumentId>
      <ActionBarPosition type="Products.Archetypes.Field.StringField">BOTTOM</ActionBarPosition>
      <HideDefaultActions type="Products.Archetypes.Field.BooleanField">True</HideDefaultActions>
      <HideInMenu type="Products.Archetypes.Field.BooleanField">True</HideInMenu>
      <isSearchForm type="Products.Archetypes.Field.BooleanField">False</isSearchForm>
      <isPage type="Products.Archetypes.Field.BooleanField">False</isPage>
      <SearchView type="Products.Archetypes.Field.StringField"/>
      <SearchFormula type="Products.Archetypes.Field.TextField"><![CDATA[]]></SearchFormula>
      <Position type="Products.Archetypes.Field.IntegerField"/>
      <ResourcesJS type="Products.Archetypes.Field.TextField"><![CDATA[]]></ResourcesJS>
      <ResourcesCSS type="Products.Archetypes.Field.TextField"><![CDATA[++resource++iol.document/css/iol.css
++resource++iol.document/css/bootstrap.css]]></ResourcesCSS>
      <excludeFromNav type="Products.Archetypes.Field.BooleanField">False</excludeFromNav>
      <elements>
        <element id="btn_save" title="Salva e completa l'istanza &gt;&gt;" type="PlominoAction">
          <id type="Products.Archetypes.Field.StringField">btn_save</id>
          <ActionType type="Products.Archetypes.Field.StringField">SAVE</ActionType>
          <ActionDisplay type="Products.Archetypes.Field.StringField">SUBMIT</ActionDisplay>
          <Content type="Products.Archetypes.Field.TextField"><![CDATA[]]></Content>
          <Hidewhen type="Products.Archetypes.Field.TextField"><![CDATA[not context.isEditMode()]]></Hidewhen>
          <InActionBar type="Products.Archetypes.Field.BooleanField">True</InActionBar>
        </element>
        <element id="btn_close" title="Chiudi" type="PlominoAction">
          <id type="Products.Archetypes.Field.StringField">btn_close</id>
          <ActionType type="Products.Archetypes.Field.StringField">CLOSE</ActionType>
          <ActionDisplay type="Products.Archetypes.Field.StringField">BUTTON</ActionDisplay>
          <Content type="Products.Archetypes.Field.TextField"><![CDATA[]]></Content>
          <Hidewhen type="Products.Archetypes.Field.TextField"><![CDATA[#context.REQUEST.get('openwithform')=='segnalazione-invio' or context.getItem('iol_workflow_status')!='compilazione']]></Hidewhen>
          <InActionBar type="Products.Archetypes.Field.BooleanField">True</InActionBar>
        </element>
        <element id="btn_edit" title="&lt;&lt; Torna in compilazione" type="PlominoAction">
          <id type="Products.Archetypes.Field.StringField">btn_edit</id>
          <ActionType type="Products.Archetypes.Field.StringField">REDIRECT</ActionType>
          <ActionDisplay type="Products.Archetypes.Field.StringField">BUTTON</ActionDisplay>
          <Content type="Products.Archetypes.Field.TextField"><![CDATA[context.doc_url()+"/EditDocument"]]></Content>
          <Hidewhen type="Products.Archetypes.Field.TextField"><![CDATA[not context.isEditMode()]]></Hidewhen>
          <InActionBar type="Products.Archetypes.Field.BooleanField">True</InActionBar>
        </element>
      </elements>
    </element>
  </design>
</plominodatabase>
